wimby/__init__.py
wimby/version.py
wimby/wimby.py
wimby-1.1.14.dist-info/LICENSE
wimby-1.1.14.dist-info/METADATA
wimby-1.1.14.dist-info/WHEEL
wimby-1.1.14.dist-info/top_level.txt
wimby-1.1.14.dist-info/RECORD
