Metadata-Version: 2.1
Name: wimby
Version: 1.1.14
Summary: Arkivist is a lightweight manager for JSON files.
Home-page: https://github.com/rmaniego/wimby
Author: Rodney Maniego Jr.
Author-email: rod.maniego23@gmail.com
License: MIT
Download-URL: https://github.com/rmaniego/wimby/archive/v1.0.tar.gz
Keywords: cryptocurrency,analytics,weighted averages
Platform: UNKNOWN
Classifier: Development Status :: 5 - Production/Stable
Classifier: Intended Audience :: Developers
Classifier: Topic :: Software Development :: Build Tools
Classifier: License :: OSI Approved :: MIT License
Classifier: Programming Language :: Python :: 3
Requires-Python: >=3.6
License-File: LICENSE
Requires-Dist: arkivist
Requires-Dist: namari
Requires-Dist: shameni
Requires-Dist: sometime
